dimorphite_dl/__init__.py
dimorphite_dl/cli.py
dimorphite_dl/dimorphite_dl.py
dimorphite_dl/site_substructures.smarts
dimorphite_ojmb-1.2.5.post1.dist-info/LICENSE.txt
dimorphite_ojmb-1.2.5.post1.dist-info/METADATA
dimorphite_ojmb-1.2.5.post1.dist-info/WHEEL
dimorphite_ojmb-1.2.5.post1.dist-info/entry_points.txt
dimorphite_ojmb-1.2.5.post1.dist-info/top_level.txt
dimorphite_ojmb-1.2.5.post1.dist-info/RECORD
