Metadata-Version: 2.1
Name: dimorphite-ojmb
Version: 1.2.5.post1
Summary: An open-source program for enumerating the ionization states of drug-like small molecules
Home-page: https://durrantlab.pitt.edu/dimorphite-dl/
Maintainer: Olivier J. M. Béquignon
Maintainer-email: "olivier.bequignon.maintainer@gmail.com"
License: MIT
Keywords: Ionization,pH,Protonation,Modeling,Virtual screening,Drug discovery
Classifier: Programming Language :: Python
Classifier: Programming Language :: Python :: 3.8
Classifier: Programming Language :: Python :: 3.7
Classifier: Programming Language :: Python :: 3.6
License-File: LICENSE.txt
Requires-Dist: tqdm
Requires-Dist: rdkit
Requires-Dist: click >=8.0.0
